directoryPy/__init__.py
directoryPy/directory.py
directorypy-0.0.1.dist-info/METADATA
directorypy-0.0.1.dist-info/WHEEL
directorypy-0.0.1.dist-info/licenses/LICENSE
directorypy-0.0.1.dist-info/RECORD
