Metadata-Version: 2.1
Name: directoryPy
Version: 0.0.1
Summary: This library is useful for working with structure of files and directories, facilitating the tasks related with those structures, such as getting information, copying, renaming and creating files and directories.
Project-URL: Homepage, https://github.com/JonaLibonati/directoryPy
Author-email: Jonathan Nicolas Libonati <libonati.jonathan@gmail.com>
License-File: LICENSE
Classifier: License :: OSI Approved :: MIT License
Classifier: Operating System :: OS Independent
Classifier: Programming Language :: Python :: 3
Requires-Python: >=3.7
